stco/__init__.py
stco/clustering.py
stco/overlay.py
stco/tests/test_clustering.py
stco/tests/test_overlay.py
stco-0.1.2.dist-info/LICENSE
stco-0.1.2.dist-info/METADATA
stco-0.1.2.dist-info/WHEEL
stco-0.1.2.dist-info/top_level.txt
stco-0.1.2.dist-info/RECORD
