Metadata-Version: 2.1
Name: stco
Version: 0.1.2
Summary: Algorithms for analyzing the stability of spatial clusters over time
Author-email: Luke Zaruba <lukeazaruba@gmail.com>
License: MIT License
Project-URL: Repository, https://github.com/lukezaruba/stco
Project-URL: Issues, https://github.com/lukezaruba/stco/issues
Keywords: GIS,geospatial,spatiotemporal,spatialdatascience
Classifier: Intended Audience :: Science/Research
Classifier: License :: OSI Approved :: MIT License
Classifier: Programming Language :: Python
Classifier: Programming Language :: Python :: 3
Classifier: Programming Language :: Python :: 3.9
Classifier: Programming Language :: Python :: 3.10
Classifier: Programming Language :: Python :: 3.11
Classifier: Topic :: Scientific/Engineering
Requires-Python: >=3.9
License-File: LICENSE
Requires-Dist: esda
Requires-Dist: geopandas
Requires-Dist: numba
Requires-Dist: numpy
Requires-Dist: pandas
Requires-Dist: shapely
Requires-Dist: tqdm
Provides-Extra: dev
Requires-Dist: black ; extra == 'dev'
Requires-Dist: flake8 ; extra == 'dev'
Requires-Dist: isort ; extra == 'dev'
Requires-Dist: pre-commit ; extra == 'dev'
